simpleaihelper/__init__.py
simpleaihelper/client.py
simpleaihelper/session.py
simpleaihelper/db/__init__.py
simpleaihelper/db/json_manager.py
simpleaihelper/db/sqlite_manager.py
simpleaihelper-0.1.0.dist-info/METADATA
simpleaihelper-0.1.0.dist-info/WHEEL
simpleaihelper-0.1.0.dist-info/top_level.txt
simpleaihelper-0.1.0.dist-info/RECORD
