Metadata-Version: 2.2
Name: simpleaihelper
Version: 0.1.0
Summary: A high-performance wrapper for OpenAI API
Home-page: https://github.com/aixiasang/simpleaihelper
Author: AI Kit Developer
Author-email: aixiasang@163.com
Classifier: Programming Language :: Python :: 3
Classifier: License :: OSI Approved :: MIT License
Classifier: Operating System :: OS Independent
Requires-Python: >=3.7
Requires-Dist: openai>=1.0.0
Dynamic: author
Dynamic: author-email
Dynamic: classifier
Dynamic: description
Dynamic: description-content-type
Dynamic: home-page
Dynamic: requires-dist
Dynamic: requires-python
Dynamic: summary
